{
  "msg": "success",
  "code": 0,
  "data": {
    "couponInfo": [{
      "couponId": 1442551834339005,
      "couponName": "优惠券",
      "couponDesc": "满10元可用\r\n每日鲜果可用\r\n进口商品可用\r\n奶饮酒水可用",
      "status": 0,
      "curTime": 1442747646000,
      "startTime": 1442246400000,
      "endTime": 1442851199000,
      "money": 300
    }, {
      "couponId": 1441679907451000,
      "couponName": "优惠券",
      "couponDesc": "全平台通用\r\n满10元可用",
      "status": 2,
      "curTime": 1442747646000,
      "startTime": 1441555200000,
      "endTime": 1442246399000,
      "money": 100
    }, {
      "couponId": 1442541439658009,
      "couponName": "优惠券",
      "couponDesc": "满12元可用\r\n每日鲜果可用\r\n进口商品可用\r\n奶饮酒水可用",
      "status": 2,
      "curTime": 1442747646000,
      "startTime": 1442246400000,
      "endTime": 1442851199000,
      "money": 500
    }, {
      "couponId": 1441868517109007,
      "couponName": "优惠券",
      "couponDesc": "全平台通用\r\n满20元可用",
      "status": 3,
      "curTime": 1442747646000,
      "startTime": 1441555200000,
      "endTime": 1442246399000,
      "money": 300
    }, {
      "couponId": 1441940187272005,
      "couponName": "优惠券",
      "couponDesc": "全平台通用\r\n满10元可用",
      "status": 3,
      "curTime": 1442747646000,
      "startTime": 1441555200000,
      "endTime": 1442246399000,
      "money": 100
    }, {
      "couponId": 1441935018680006,
      "couponName": "优惠券",
      "couponDesc": "全平台通用\r\n满20元可用",
      "status": 3,
      "curTime": 1442747646000,
      "startTime": 1441555200000,
      "endTime": 1442246399000,
      "money": 300
    }, {
      "couponId": 1441888955520002,
      "couponName": "优惠券",
      "couponDesc": "全平台通用\r\n满15元可用",
      "status": 3,
      "curTime": 1442747646000,
      "startTime": 1441555200000,
      "endTime": 1442246399000,
      "money": 200
    }, {
      "couponId": 1442041136968009,
      "couponName": "优惠券",
      "couponDesc": "全平台通用\r\n满10元可用",
      "status": 3,
      "curTime": 1442747646000,
      "startTime": 1441555200000,
      "endTime": 1442246399000,
      "money": 100
    }, {
      "couponId": 1441868517109001,
      "couponName": "优惠券",
      "couponDesc": "全平台通用\r\n满10元可用",
      "status": 3,
      "curTime": 1442747646000,
      "startTime": 1441555200000,
      "endTime": 1442246399000,
      "money": 100
    }, {
      "couponId": 1441868047548007,
      "couponName": "优惠券",
      "couponDesc": "全平台通用\r\n满10元可用",
      "status": 3,
      "curTime": 1442747646000,
      "startTime": 1441555200000,
      "endTime": 1442246399000,
      "money": 100
    }, {
      "couponId": 1441853853648005,
      "couponName": "优惠券",
      "couponDesc": "全平台通用\r\n满20元可用",
      "status": 3,
      "curTime": 1442747646000,
      "startTime": 1441555200000,
      "endTime": 1442246399000,
      "money": 300
    }, {
      "couponId": 1441853070219006,
      "couponName": "优惠券",
      "couponDesc": "全平台通用\r\n满15元可用",
      "status": 3,
      "curTime": 1442747646000,
      "startTime": 1441555200000,
      "endTime": 1442246399000,
      "money": 200
    }, {
      "couponId": 1441767648709008,
      "couponName": "优惠券",
      "couponDesc": "全平台通用\r\n满15元可用",
      "status": 3,
      "curTime": 1442747646000,
      "startTime": 1441555200000,
      "endTime": 1442246399000,
      "money": 200
    }, {
      "couponId": 1441767262998003,
      "couponName": "优惠券",
      "couponDesc": "全平台通用\r\n满10元可用",
      "status": 3,
      "curTime": 1442747646000,
      "startTime": 1441555200000,
      "endTime": 1442246399000,
      "money": 100
    }, {
      "couponId": 1441961353087007,
      "couponName": "优惠券",
      "couponDesc": "全平台通用\r\n满15元可用",
      "status": 3,
      "curTime": 1442747646000,
      "startTime": 1441555200000,
      "endTime": 1442246399000,
      "money": 200
    }]
  },
  "serverTime": "2015-09-20 19:14:06"
}
